LICENSE
MANIFEST.in
README.rst
dj_search_url.py
setup.py
dj_searchurl.egg-info/PKG-INFO
dj_searchurl.egg-info/SOURCES.txt
dj_searchurl.egg-info/dependency_links.txt
dj_searchurl.egg-info/not-zip-safe
dj_searchurl.egg-info/requires.txt
dj_searchurl.egg-info/top_level.txt